setup.py
vertica_sqlalchemy_0.2.egg-info/PKG-INFO
vertica_sqlalchemy_0.2.egg-info/SOURCES.txt
vertica_sqlalchemy_0.2.egg-info/dependency_links.txt
vertica_sqlalchemy_0.2.egg-info/entry_points.txt
vertica_sqlalchemy_0.2.egg-info/requires.txt
vertica_sqlalchemy_0.2.egg-info/top_level.txt
verticasa/__init__.py
verticasa/verticasa.py