Metadata-Version: 1.0
Name: vertica-sqlalchemy-0.2
Version: 0.2
Summary: Vertica dialect for sqlalchemy
Home-page: https://bitbucket.com/shivamshukla/vertica-sqlalchemy-hpcs
Author: Shivam Shukla
Author-email: shivam.shukla@globallogic.com
License: MIT
Platform: UNKNOWN
Classifier: Development Status :: 3 - Alpha
Classifier: Intended Audience :: Developers
Classifier: License :: OSI Approved :: MIT License
Classifier: Operating System :: OS Independent
Classifier: Programming Language :: Python
